xtce_codec/__init__.py
xtce_codec/__init__.pyi
xtce_codec/py.typed
xtce_codec/xtce_codec.cpython-310-arm-linux-gnueabihf.so
xtce_codec-0.1.0.dist-info/METADATA
xtce_codec-0.1.0.dist-info/WHEEL
xtce_codec-0.1.0.dist-info/licenses/LICENSE
xtce_codec-0.1.0.dist-info/RECORD
