Metadata-Version: 2.4
Name: xtce-codec
Version: 0.1.0
Classifier: Programming Language :: Rust
Classifier: Programming Language :: Python :: Implementation :: CPython
Classifier: Programming Language :: Python :: Implementation :: PyPy
Requires-Dist: maturin>=1.9.6 ; extra == 'dev'
Requires-Dist: mypy>=1.0.0 ; extra == 'dev'
Provides-Extra: dev
License-File: LICENSE
Summary: Handles all encoding and decoding types and structures defined in the XTCE standard.
License-Expression: MIT
Requires-Python: >=3.8
Project-URL: Homepage, https://github.com/nrmiersen/xtce-codec
Project-URL: Repository, https://github.com/nrmiersen/xtce-codec
